icypher/__init__.py
icypher-0.1.6.1.dist-info/AUTHORS.rst
icypher-0.1.6.1.dist-info/LICENSE.rst
icypher-0.1.6.1.dist-info/METADATA
icypher-0.1.6.1.dist-info/WHEEL
icypher-0.1.6.1.dist-info/top_level.txt
icypher-0.1.6.1.dist-info/RECORD
