Metadata-Version: 2.1
Name: icypher
Version: 0.1.6.1
Summary: Cypher access to Neo4j via IPython
Home-page: https://github.com/lebedov/icypher/
Author: Lev E. Givon
Author-email: lev@columbia.edu
License: BSD
Platform: UNKNOWN
Classifier: Development Status :: 3 - Alpha
Classifier: Environment :: Console
Classifier: Framework :: IPython
Classifier: Intended Audience :: Developers
Classifier: License :: OSI Approved :: BSD License
Classifier: Operating System :: OS Independent
Classifier: Programming Language :: Python
Classifier: Programming Language :: Python :: 3
Classifier: Topic :: Software Development
Classifier: Topic :: Database
Classifier: Topic :: Database :: Front-Ends
Requires-Dist: ipython (>=4.0)
Requires-Dist: py2neo (>=3.0)
